odoo8_addon_business_requirement_deliverable_resource_template-8.0.1.0.1-py2.7-nspkg.pth
odoo8_addon_business_requirement_deliverable_resource_template-8.0.1.0.1.dist-info/DESCRIPTION.rst
odoo8_addon_business_requirement_deliverable_resource_template-8.0.1.0.1.dist-info/METADATA
odoo8_addon_business_requirement_deliverable_resource_template-8.0.1.0.1.dist-info/RECORD
odoo8_addon_business_requirement_deliverable_resource_template-8.0.1.0.1.dist-info/WHEEL
odoo8_addon_business_requirement_deliverable_resource_template-8.0.1.0.1.dist-info/metadata.json
odoo8_addon_business_requirement_deliverable_resource_template-8.0.1.0.1.dist-info/namespace_packages.txt
odoo8_addon_business_requirement_deliverable_resource_template-8.0.1.0.1.dist-info/top_level.txt
odoo_addons/business_requirement_deliverable_resource_template/README.rst
odoo_addons/business_requirement_deliverable_resource_template/__init__.py
odoo_addons/business_requirement_deliverable_resource_template/__openerp__.py
odoo_addons/business_requirement_deliverable_resource_template/i18n/sl.po
odoo_addons/business_requirement_deliverable_resource_template/models/__init__.py
odoo_addons/business_requirement_deliverable_resource_template/models/business_requirement_resource_template.py
odoo_addons/business_requirement_deliverable_resource_template/models/product_template.py
odoo_addons/business_requirement_deliverable_resource_template/security/ir.model.access.csv
odoo_addons/business_requirement_deliverable_resource_template/static/description/icon.png
odoo_addons/business_requirement_deliverable_resource_template/static/img/bus_req_default.png
odoo_addons/business_requirement_deliverable_resource_template/static/img/bus_req_default2.png
odoo_addons/business_requirement_deliverable_resource_template/tests/__init__.py
odoo_addons/business_requirement_deliverable_resource_template/tests/test_br_resource_template.py
odoo_addons/business_requirement_deliverable_resource_template/views/business_requirement_deliverable_default.xml
